dataenforce/__init__.py
dataenforce-0.1.2.dist-info/LICENSE
dataenforce-0.1.2.dist-info/METADATA
dataenforce-0.1.2.dist-info/WHEEL
dataenforce-0.1.2.dist-info/top_level.txt
dataenforce-0.1.2.dist-info/RECORD
