Metadata-Version: 2.1
Name: dataenforce
Version: 0.1.2
Summary: Enforce column names & data types of pandas DataFrames
Home-page: https://github.com/CedricFR/dataenforce
Author: Cedric Canovas
Author-email: dev@canovas.me
License: UNKNOWN
Platform: UNKNOWN
Classifier: Programming Language :: Python :: 3
Classifier: Operating System :: OS Independent
Classifier: License :: OSI Approved :: Apache Software License
